dxlfiletransferservice/__init__.py
dxlfiletransferservice/__main__.py
dxlfiletransferservice/_version.py
dxlfiletransferservice/app.py
dxlfiletransferservice/requesthandlers.py
dxlfiletransferservice/_config/__init__.py
dxlfiletransferservice/_config/app/__init__.py
dxlfiletransferservice/_config/app/dxlclient.config
dxlfiletransferservice/_config/app/dxlfiletransferservice.config
dxlfiletransferservice/_config/app/logging.config
dxlfiletransferservice/_config/sample/__init__.py
dxlfiletransferservice/_config/sample/dxlclient.config
dxlfiletransferservice-0.1.1.dist-info/METADATA
dxlfiletransferservice-0.1.1.dist-info/RECORD
dxlfiletransferservice-0.1.1.dist-info/WHEEL
dxlfiletransferservice-0.1.1.dist-info/top_level.txt
