Metadata-Version: 2.1
Name: dxlfiletransferservice
Version: 0.1.1
Summary: File Transfer DXL Python service
Home-page: https://www.opendxl.com
Author: Jeremy Barlow
License: Apache License 2.0
Keywords: opendxl,dxl,service,file,transfer
Platform: UNKNOWN
Classifier: Development Status :: 4 - Beta
Classifier: Topic :: Software Development :: Libraries :: Python Modules
Classifier: Programming Language :: Python
Classifier: Programming Language :: Python :: 2
Classifier: Programming Language :: Python :: 2.7
Classifier: Programming Language :: Python :: 3
Classifier: Programming Language :: Python :: 3.4
Classifier: Programming Language :: Python :: 3.5
Classifier: Programming Language :: Python :: 3.6
Requires-Python: >=2.7.9,!=3.0.*,!=3.1.*,!=3.2.*,!=3.3.*
Provides-Extra: test
Provides-Extra: dev
Requires-Dist: dxlbootstrap (>=0.2.0)
Requires-Dist: dxlclient (>=4.1.0.184)
Requires-Dist: dxlfiletransferclient
Provides-Extra: dev
Requires-Dist: mock; extra == 'dev'
Requires-Dist: nose; extra == 'dev'
Requires-Dist: pylint; extra == 'dev'
Requires-Dist: sphinx; extra == 'dev'
Provides-Extra: test
Requires-Dist: mock; extra == 'test'
Requires-Dist: nose; extra == 'test'
Requires-Dist: pylint; extra == 'test'
